[
  {
    "text": "こういう重大な事故を起こしたら、 免許返納 や再審査を 義務化 するくらい厳しくてもいいと思う。",
    "tweet_id": "2069316466042904934",
    "url": "https://x.com/PsyDuckisking/status/2069316466042904934",
    "original_category": "免許返納義務化に賛成（高齢運転手の事故防止を最優先）",
    "original_stance": "義務化賛成",
    "is_opinion": true,
    "stance_restriction": 1.0,
    "stance_priority": 1.0,
    "emotional_intensity": 0.5,
    "confidence": 0.85,
    "summary": "重大事故後の免許返納義務化支持"
  },
  {
    "text": "どうでもいい法案ばっかり通して。 「それより８５歳以上の 免許返納 を 義務化 してほしいものだよねー。」 と、夫と話した今日この頃。 https://t.co/YUtmkC3Roz",
    "tweet_id": "2067548872151634344",
    "url": "https://x.com/senchanpe/status/2067548872151634344",
    "original_category": "免許返納義務化に賛成（高齢運転手の事故防止を最優先）",
    "original_stance": "義務化賛成",
    "is_opinion": true,
    "stance_restriction": 2.0,
    "stance_priority": 2.0,
    "emotional_intensity": 1.0,
    "confidence": 0.85,
    "summary": "８５歳以上の免許返納義務化を強く要望"
  },
  {
    "text": "介護に長年従事してるけど高齢者の 免許返納 は 義務化 するべき https://t.co/PhKDBGDoXg",
    "tweet_id": "2067239970751037498",
    "url": "https://x.com/pGyPV4ZWUcdozJ1/status/2067239970751037498",
    "original_category": "免許返納義務化に賛成（高齢運転手の事故防止を最優先）",
    "original_stance": "義務化賛成",
    "is_opinion": true,
    "stance_restriction": 2.0,
    "stance_priority": 1.5,
    "emotional_intensity": 1.0,
    "confidence": 0.9,
    "summary": "介護従事者が返納義務化を提案"
  },
  {
    "text": "どんな衝撃だっただろうか……事故した瞬間は本当に怖かっただろうな。高齢者に大事な未来ある命を奪われなくて本当に良かった。高齢者の 免許返納義務化 してほしい。 https://t.co/DJrKXH9LAB",
    "tweet_id": "2067182907178000531",
    "url": "https://x.com/ebifry_away/status/2067182907178000531",
    "original_category": "免許返納義務化に賛成（高齢運転手の事故防止を最優先）",
    "original_stance": "義務化賛成",
    "is_opinion": true,
    "stance_restriction": 2.0,
    "stance_priority": 2.0,
    "emotional_intensity": 1.5,
    "confidence": 0.85,
    "summary": "事故の恐怖から高齢者免許返納義務化を強く支持"
  },
  {
    "text": "どうせお偉いさん方の懐行きじゃん その前に外国人規制と高齢者の 免許返納義務化 しろよ、あとループ廃止",
    "tweet_id": "2067181921357156819",
    "url": "https://x.com/15milkoco/status/2067181921357156819",
    "original_category": "免許返納義務化に賛成（高齢運転手の事故防止を最優先）",
    "original_stance": "義務化賛成",
    "is_opinion": true,
    "stance_restriction": 1.0,
    "stance_priority": 1.0,
    "emotional_intensity": 1.0,
    "confidence": 0.7,
    "summary": "政策批判と返納義務化求める投稿"
  },
  {
    "text": "免許返納 も年齢や運動機能に合わせて 義務化 するべき！！！！ さすがにふつうに歩けない人ダメでしょ",
    "tweet_id": "2066740456185340235",
    "url": "https://x.com/nish_i1106/status/2066740456185340235",
    "original_category": "免許返納義務化に賛成（高齢運転手の事故防止を最優先）",
    "original_stance": "義務化賛成",
    "is_opinion": true,
    "stance_restriction": 2.0,
    "stance_priority": 2.0,
    "emotional_intensity": 1.5,
    "confidence": 0.85,
    "summary": "運転能力低下者の免許返納義務化を求める怒りの投稿"
  },
  {
    "text": "2人の命が奪われているのに、85歳だからと刑事責任能力を疑うの？高齢運転手の事故が多すぎる。もっと厳罰化して、 免許返納 を 義務化 すべき。被害者が可哀想すぎる。",
    "tweet_id": "2064889145395384511",
    "url": "https://x.com/thinvn1/status/2064889145395384511",
    "original_category": "免許返納義務化に賛成（高齢運転手の事故防止を最優先）",
    "original_stance": "義務化賛成",
    "is_opinion": true,
    "stance_restriction": 2.0,
    "stance_priority": 2.0,
    "emotional_intensity": 2.0,
    "confidence": 0.95,
    "summary": "義務返納と厳罰化を強く求める怒りの意見"
  },
  {
    "text": "悲惨な高齢者ドライバーの事故から子供たちを守るために。 ​自動運転と一番相性が良いのは、制御が精密なEV。 『高齢者は 免許返納 』ではなく、『高齢者はガソリン車運転しちゃダメ、EVの自動運転しか乗っちゃダメ』という 義務化 に舵を切ってほしい。技術はあるんだから、あとは政治と仕組みの問題。",
    "tweet_id": "2064654467111559494",
    "url": "https://x.com/minto_kun0617/status/2064654467111559494",
    "original_category": "適性検査や技術的制限の強化で対応（年齢一律の義務化は避けるべき）",
    "original_stance": "適性検査強化",
    "is_opinion": true,
    "stance_restriction": 2.0,
    "stance_priority": 2.0,
    "emotional_intensity": 1.0,
    "confidence": 0.85,
    "summary": "高齢者EV自动驾驶の法的義務化を強く主張"
  },
  {
    "text": "けが人がいなかったのは本当に奇跡だけど、78歳で運転操作ミスは他人事じゃないよね。そろそろ年齢での 免許返納 を 義務化 するか、サポカー限定にする議論を本気で進めてほしい。",
    "tweet_id": "2063532471581585713",
    "url": "https://x.com/thinvn1/status/2063532471581585713",
    "original_category": "免許返納義務化に賛成（高齢運転手の事故防止を最優先）",
    "original_stance": "義務化賛成",
    "is_opinion": true,
    "stance_restriction": 2.0,
    "stance_priority": 2.0,
    "emotional_intensity": 1.0,
    "confidence": 0.9,
    "summary": "78歳事故を契機に返納義務化を強く主張"
  },
  {
    "text": "逆走したり、人を巻き込んだり、能力が衰えてるんだから 免許返納 を 義務化 すべきだろう。",
    "tweet_id": "2062792816590459200",
    "url": "https://x.com/mu_xia31408/status/2062792816590459200",
    "original_category": "免許返納義務化に賛成（高齢運転手の事故防止を最優先）",
    "original_stance": "義務化賛成",
    "is_opinion": true,
    "stance_restriction": 2.0,
    "stance_priority": 2.0,
    "emotional_intensity": 1.0,
    "confidence": 0.85,
    "summary": "返納義務化支持、安全最優先の主張"
  },
  {
    "text": "免許返納 の 義務化 をしないとダメですね",
    "tweet_id": "2062746738272927757",
    "url": "https://x.com/ZuoChuan90857/status/2062746738272927757",
    "original_category": "免許返納義務化に賛成（高齢運転手の事故防止を最優先）",
    "original_stance": "義務化賛成",
    "is_opinion": true,
    "stance_restriction": 2.0,
    "stance_priority": 1.0,
    "emotional_intensity": 1.0,
    "confidence": 0.7,
    "summary": "免許返納義務化の必要性を訴える安全重視の意見"
  },
  {
    "text": "70歳過ぎたら 免許返納義務化 にすべき。細かい事情は不要",
    "tweet_id": "2061831742349267281",
    "url": "https://x.com/Un90713/status/2061831742349267281",
    "original_category": "免許返納義務化に賛成（高齢運転手の事故防止を最優先）",
    "original_stance": "義務化賛成",
    "is_opinion": true,
    "stance_restriction": 2.0,
    "stance_priority": 2.0,
    "emotional_intensity": 1.0,
    "confidence": 0.95,
    "summary": "70歳以上返納義務化を主張"
  },
  {
    "text": "マジで 免許返納義務化 して😭🙏",
    "tweet_id": "2061657556028936668",
    "url": "https://x.com/Chokemaru_24/status/2061657556028936668",
    "original_category": "免許返納義務化に賛成（高齢運転手の事故防止を最優先）",
    "original_stance": "義務化賛成",
    "is_opinion": true,
    "stance_restriction": 2.0,
    "stance_priority": 1.0,
    "emotional_intensity": 2.0,
    "confidence": 0.7,
    "summary": "高齢者の免許返納義務化を強く支持する感情的な投稿"
  },
  {
    "text": "無条件で80歳以上の 免許返納 を 義務化 すべきだろ スイミングスクールも85歳をよく運転手で雇おうとしたな https://t.co/ZdRz6n1QBN",
    "tweet_id": "2061584797508731197",
    "url": "https://x.com/teracho_g24/status/2061584797508731197",
    "original_category": "免許返納義務化に賛成（高齢運転手の事故防止を最優先）",
    "original_stance": "義務化賛成",
    "is_opinion": true,
    "stance_restriction": 2.0,
    "stance_priority": 2.0,
    "emotional_intensity": 1.0,
    "confidence": 0.85,
    "summary": "80歳以上無条件返納義務化を求め安全最優先"
  },
  {
    "text": "75歳 免許返納義務化 を求めます❣️ https://t.co/b3SRP4sXI9",
    "tweet_id": "2061343452156293543",
    "url": "https://x.com/junchi1029/status/2061343452156293543",
    "original_category": "免許返納義務化に賛成（高齢運転手の事故防止を最優先）",
    "original_stance": "義務化賛成",
    "is_opinion": true,
    "stance_restriction": 2.0,
    "stance_priority": 2.0,
    "emotional_intensity": 1.0,
    "confidence": 0.9,
    "summary": "75歳に免許返納の法的義務化を求める主張"
  },
  {
    "text": "自動車免許取得できる年齢が決まっとるように、免許返すのを 義務化 したほうがいい 70歳以降はマニュアル車限定　80歳で 免許返納 車が必須の場所は特例(ドリフト走行・Ｓ字は3速・クランクはバックで等、試験落ちたら即返納)",
    "tweet_id": "2061328042170233146",
    "url": "https://x.com/_democrash/status/2061328042170233146",
    "original_category": "免許返納義務化に賛成（高齢運転手の事故防止を最優先）",
    "original_stance": "義務化賛成",
    "is_opinion": true,
    "stance_restriction": 2.0,
    "stance_priority": 2.0,
    "emotional_intensity": 1.0,
    "confidence": 0.9,
    "summary": "年齢での免許返納義務化を提案する安全的意見"
  },
  {
    "text": "対して何故 免許返納 を努力 義務化 しないのかと思う。例えば85歳で運転したとて足腰が覚束無い状況ならば普通は政府が率先垂範して影響を80-90代に対しては止めさせる仕組み作りを加速させる可きなのに何処ぞの高市早苗は全く其れ障もしないで馬鹿の一つ覚えで高齢者の尊厳性がとか話しているのだから https://t.co/69ZydHIJCx",
    "tweet_id": "2061022537199542593",
    "url": "https://x.com/gandamuotaku83/status/2061022537199542593",
    "original_category": "免許返納義務化に賛成（高齢運転手の事故防止を最優先）",
    "original_stance": "義務化賛成",
    "is_opinion": true,
    "stance_restriction": 2.0,
    "stance_priority": 1.5,
    "emotional_intensity": 1.5,
    "confidence": 0.85,
    "summary": "高齢者の免許返納強制を政府主導で進めるべきと強く主張"
  },
  {
    "text": "高齢者の自動車事故が後を経ちません。 例えば2025年の統計では、75歳以上の高齢運転者による死亡事故は397件。 安全装置搭載車での運転 義務化 や、 免許返納 の 義務化 など、 行政と企業でも本気で子供の命を守って欲しい https://t.co/5OyAKmTOd0",
    "tweet_id": "2060863711800439172",
    "url": "https://x.com/sono_ayapi/status/2060863711800439172",
    "original_category": "免許返納義務化に賛成（高齢運転手の事故防止を最優先）",
    "original_stance": "義務化賛成",
    "is_opinion": true,
    "stance_restriction": 1.5,
    "stance_priority": 2.0,
    "emotional_intensity": 1.0,
    "confidence": 0.85,
    "summary": "高齢事故の統計を示し、義務化による子供保護を求める意見"
  },
  {
    "text": "もう 免許返納義務化 して欲しい…",
    "tweet_id": "2060855019784814635",
    "url": "https://x.com/DoraShiba0909/status/2060855019784814635",
    "original_category": "免許返納義務化に賛成（高齢運転手の事故防止を最優先）",
    "original_stance": "義務化賛成",
    "is_opinion": true,
    "stance_restriction": 2.0,
    "stance_priority": 1.0,
    "emotional_intensity": 1.0,
    "confidence": 0.7,
    "summary": "義務化を強く望む切実な意見"
  },
  {
    "text": "ヤバ過ぎる😨 免許返納義務化 も検討しないと",
    "tweet_id": "2060853489312641161",
    "url": "https://x.com/24chokemaru/status/2060853489312641161",
    "original_category": "免許返納義務化に賛成（高齢運転手の事故防止を最優先）",
    "original_stance": "義務化賛成",
    "is_opinion": true,
    "stance_restriction": 1.0,
    "stance_priority": 0.0,
    "emotional_intensity": 1.0,
    "confidence": 0.5,
    "summary": "事故防止へ義務化検討を支持する驚きの意見"
  },
  {
    "text": "やっぱり 免許返納義務化 しなきゃ… 高齢者の事故が多すぎる…",
    "tweet_id": "2060833757150826800",
    "url": "https://x.com/DoraShiba0909/status/2060833757150826800",
    "original_category": "免許返納義務化に賛成（高齢運転手の事故防止を最優先）",
    "original_stance": "義務化賛成",
    "is_opinion": true,
    "stance_restriction": 2.0,
    "stance_priority": 2.0,
    "emotional_intensity": 1.0,
    "confidence": 0.9,
    "summary": "免許返納義務化を支持、事故防止重視"
  },
  {
    "text": "免許返納義務化 しろ！！！！！ https://t.co/hMPYKuMTg4",
    "tweet_id": "2060832634113282390",
    "url": "https://x.com/snowfff_/status/2060832634113282390",
    "original_category": "免許返納義務化に賛成（高齢運転手の事故防止を最優先）",
    "original_stance": "義務化賛成",
    "is_opinion": true,
    "stance_restriction": 2.0,
    "stance_priority": 2.0,
    "emotional_intensity": 2.0,
    "confidence": 0.9,
    "summary": "返納義務化を強く求める感情的な投稿"
  },
  {
    "text": "だからもう何回も言ってるけど、免許所持と選挙権は上限つけろよ 70歳以上の 免許返納義務化 にしろよ https://t.co/WUTcHBeLGw",
    "tweet_id": "2060744506736333095",
    "url": "https://x.com/city5353/status/2060744506736333095",
    "original_category": "免許返納義務化に賛成（高齢運転手の事故防止を最優先）",
    "original_stance": "義務化賛成",
    "is_opinion": true,
    "stance_restriction": 2.0,
    "stance_priority": 1.5,
    "emotional_intensity": 1.5,
    "confidence": 0.85,
    "summary": "70歳以上の免許返納義務化を求める強い主張"
  },
  {
    "text": "やっぱ60歳での 免許返納義務化 した方が良いと思う",
    "tweet_id": "2060741373863870868",
    "url": "https://x.com/ultra_Bocchi/status/2060741373863870868",
    "original_category": "免許返納義務化に賛成（高齢運転手の事故防止を最優先）",
    "original_stance": "義務化賛成",
    "is_opinion": true,
    "stance_restriction": 2.0,
    "stance_priority": 1.0,
    "emotional_intensity": 0.5,
    "confidence": 0.85,
    "summary": "60歳での免許返納義務化を推進する意見"
  },
  {
    "text": "ジジイが運転すんなや マジで 免許返納義務化 せんとじゃんじゃん起きるぞ？ 義務化 した所で乗り続ける奴居るかもだが https://t.co/T3LidzZ0vh",
    "tweet_id": "2060635259990069757",
    "url": "https://x.com/wolf36732/status/2060635259990069757",
    "original_category": "免許返納義務化に賛成（高齢運転手の事故防止を最優先）",
    "original_stance": "義務化賛成",
    "is_opinion": true,
    "stance_restriction": 2.0,
    "stance_priority": 2.0,
    "emotional_intensity": 2.0,
    "confidence": 0.9,
    "summary": "高齢者の強制返納義務化を求める怒りの投稿"
  },
  {
    "text": "最近お年寄りが加害者になる交通事故が目立ちますね 年齢での 免許返納 を 義務化 すればいいのに🤔",
    "tweet_id": "2060620363378409966",
    "url": "https://x.com/nobuko22128/status/2060620363378409966",
    "original_category": "免許返納義務化に賛成（高齢運転手の事故防止を最優先）",
    "original_stance": "義務化賛成",
    "is_opinion": true,
    "stance_restriction": 2.0,
    "stance_priority": 2.0,
    "emotional_intensity": 1.0,
    "confidence": 0.85,
    "summary": "年齢で返納を義務化すべきとの意見"
  },
  {
    "text": "高齢者による運転ミスの事故は悲しいです🐱 免許返納 の 義務化 は必須です🐱",
    "tweet_id": "2060581426144411823",
    "url": "https://x.com/ideco_cat/status/2060581426144411823",
    "original_category": "免許返納義務化に賛成（高齢運転手の事故防止を最優先）",
    "original_stance": "義務化賛成",
    "is_opinion": true,
    "stance_restriction": 2.0,
    "stance_priority": 2.0,
    "emotional_intensity": 1.0,
    "confidence": 0.9,
    "summary": "返納義務化と安全最優先を明確に支持"
  },
  {
    "text": "普通車は生活に必要な人もいるからしょうがないとはいえ、中型・大型とかは80なった時点で 免許返納義務化 しろよ… https://t.co/lB5QKNEL0t",
    "tweet_id": "2060563655725654136",
    "url": "https://x.com/Quagsirelover11/status/2060563655725654136",
    "original_category": "免許返納義務化に賛成（高齢運転手の事故防止を最優先）",
    "original_stance": "義務化賛成",
    "is_opinion": true,
    "stance_restriction": 2.0,
    "stance_priority": 2.0,
    "emotional_intensity": 1.0,
    "confidence": 0.8,
    "summary": "80歳で中型・大型の返納義務化を強く主張"
  },
  {
    "text": "８０歳以上は 免許返納義務化 にすべきだよ、、 そして、８０代以上の方が、それで生活に不自由しないような社会づくりを頑張っていくべきだよ、、",
    "tweet_id": "2060556926380024074",
    "url": "https://x.com/intenti33310775/status/2060556926380024074",
    "original_category": "免許返納義務化に賛成（高齢運転手の事故防止を最優先）",
    "original_stance": "義務化賛成",
    "is_opinion": true,
    "stance_restriction": 2.0,
    "stance_priority": 1.0,
    "emotional_intensity": 1.0,
    "confidence": 0.85,
    "summary": "80歳以上への免許返納義務化と社会支援を求める投稿"
  },
  {
    "text": "法律で高齢ドライバーは 免許返納 を 義務化 してほしい。何人犠牲になれば法律が変わるんだろう。もういい加減にして欲しい。 https://t.co/UWn4hoz4Dm",
    "tweet_id": "2060349575144313311",
    "url": "https://x.com/snowfff_/status/2060349575144313311",
    "original_category": "免許返納義務化に賛成（高齢運転手の事故防止を最優先）",
    "original_stance": "義務化賛成",
    "is_opinion": true,
    "stance_restriction": 2.0,
    "stance_priority": 2.0,
    "emotional_intensity": 2.0,
    "confidence": 0.95,
    "summary": "法的義務化を求め感情的に批判する投稿"
  },
  {
    "text": "いつになったら高齢者の運転 免許 、 返納義務化 されるんだろう…老害は国で規てくれよ… https://t.co/Wt5iTDCzDz",
    "tweet_id": "2060348964772421968",
    "url": "https://x.com/snowfff_/status/2060348964772421968",
    "original_category": "免許返納義務化に賛成（高齢運転手の事故防止を最優先）",
    "original_stance": "義務化賛成",
    "is_opinion": true,
    "stance_restriction": 2.0,
    "stance_priority": 2.0,
    "emotional_intensity": 2.0,
    "confidence": 0.9,
    "summary": "高齢者の免許返納義務化求め怒り示す"
  },
  {
    "text": "【危険運転】ルール無視で歩道を車で走るお婆さん、一歩間違えれば死人が出る事態になりかねない 高齢者は 免許返納 の 義務化 が必要な模様。 後ろにディオでも乗ってんのか？ #危険運転 #高齢者 https://t.co/DolvhMpNS9 https://t.co/fYED8p4xeh",
    "tweet_id": "1738809260883190074",
    "url": "https://x.com/bakusai_com/status/1738809260883190074",
    "original_category": "免許返納義務化に賛成（高齢運転手の事故防止を最優先）",
    "original_stance": "義務化賛成",
    "is_opinion": true,
    "stance_restriction": 1.5,
    "stance_priority": 1.5,
    "emotional_intensity": 1.5,
    "confidence": 0.85,
    "summary": "危険運転警告後に高齢者の免許返納義務化を求める"
  },
  {
    "text": "「高齢ドライバーの事故、どう防ぐ」簡単です。70歳以上は 免許返納義務化 で解決です。 逆に70歳を過ぎても自動車を利用させてると、電車やバス・徒歩での移動が困難になり、生涯自動車に依存する事になります。 今の政治家にこういう事考えられる人はいないでしょうけどね。",
    "tweet_id": "1580374661178982400",
    "url": "https://x.com/GraffiasRear/status/1580374661178982400",
    "original_category": "免許返納義務化に賛成（高齢運転手の事故防止を最優先）",
    "original_stance": "義務化賛成",
    "is_opinion": true,
    "stance_restriction": 2.0,
    "stance_priority": 2.0,
    "emotional_intensity": 1.0,
    "confidence": 0.95,
    "summary": "70歳返納義務化を強く支持、安全最優先"
  },
  {
    "text": "俺も 高齢者 の 免許返納 には 賛成 です🙂‍↕️",
    "tweet_id": "2061773776921280838",
    "url": "https://x.com/Gk6Ams/status/2061773776921280838",
    "original_category": "免許返納義務化に賛成（高齢運転手の事故防止を最優先）",
    "original_stance": "義務化賛成",
    "is_opinion": true,
    "stance_restriction": 1.0,
    "stance_priority": 1.0,
    "emotional_intensity": 1.0,
    "confidence": 0.7,
    "summary": "高齢者の免許返納賛成表明"
  },
  {
    "text": "やっぱ俺は 高齢者 の 免許返納 には 賛成 です https://t.co/Xwv2500iUP",
    "tweet_id": "2061745951119937868",
    "url": "https://x.com/hagidaiki/status/2061745951119937868",
    "original_category": "免許返納義務化に賛成（高齢運転手の事故防止を最優先）",
    "original_stance": "義務化賛成",
    "is_opinion": true,
    "stance_restriction": 1.0,
    "stance_priority": 1.0,
    "emotional_intensity": 0.5,
    "confidence": 0.7,
    "summary": "高齢者免許返納賛成の個人的意見"
  },
  {
    "text": "「田舎で足がなくなると生活できなくなるから、 高齢者免許返納 できない」 これに 賛成 できないが一歩譲って認めるとしても、近所の買い物と病院に通うだけ、すなわち同じ経路のみの利用にしてください けっこう遊びに行ったり大型買い物施設に行ったりで事故起こしている 高齢者 が見受けられます",
    "tweet_id": "2060768487430373720",
    "url": "https://x.com/NRVYC5XYAkTDIHD/status/2060768487430373720",
    "original_category": "免許返納義務化に反対（地方の生活維持や移動手段確保を重視）",
    "original_stance": "義務化反対",
    "is_opinion": true,
    "stance_restriction": 1.0,
    "stance_priority": 1.0,
    "emotional_intensity": 0.5,
    "confidence": 0.75,
    "summary": "地方高齢者の移動権認めつつ利用制限求める"
  },
  {
    "text": "公園の駐車場で車の 高齢者 が２才児を轢いて死亡させる事故。 高齢者 の 免許返納 を言うのと、２才児を見守らない親を非難する意見が出ている。 どちらが一方的に過失があったかどうか。両者に同じ割合の過失があったかもしれない。 年齢一律で 免許返納 には 反対 。更新時の検査を厳密にすればと思う。",
    "tweet_id": "2060626741530616094",
    "url": "https://x.com/dare_iwan/status/2060626741530616094",
    "original_category": "適性検査や技術的制限の強化で対応（年齢一律の義務化は避けるべき）",
    "original_stance": "適性検査強化",
    "is_opinion": true,
    "stance_restriction": -2.0,
    "stance_priority": 0.0,
    "emotional_intensity": 0.0,
    "confidence": 0.85,
    "summary": "年齢一律返納に反対。両者に過失の可能性がある。"
  },
  {
    "text": "高齢者の車の事故が多いな… 年齢制限 で 免許返納 した方がいいかも⁉️ #高齢者事故",
    "tweet_id": "2068577328616382626",
    "url": "https://x.com/rZvt4IEQnj45472/status/2068577328616382626",
    "original_category": "免許返納義務化に賛成（高齢運転手の事故防止を最優先）",
    "original_stance": "義務化賛成",
    "is_opinion": true,
    "stance_restriction": 1.0,
    "stance_priority": 1.0,
    "emotional_intensity": 0.0,
    "confidence": 0.6,
    "summary": "高齢者の事故増加に懸念し年齢制限による返納を提案"
  },
  {
    "text": "やっぱり免許の 年齢制限 は必須だわ( 免許返納 ) 先日私も高齢者の運転に轢かれそうになった 横断歩道渡ってるのに突っ込んできたよ 1人でしんでくれよな！巻き込まないでくれ！ https://t.co/1mo02t7k3p",
    "tweet_id": "2067493363344191518",
    "url": "https://x.com/cP2ELZsMlRrDWQ1/status/2067493363344191518",
    "original_category": "免許返納義務化に賛成（高齢運転手の事故防止を最優先）",
    "original_stance": "義務化賛成",
    "is_opinion": true,
    "stance_restriction": 2.0,
    "stance_priority": 2.0,
    "emotional_intensity": 2.0,
    "confidence": 0.95,
    "summary": "自身の危険体験に基づく年齢制限・義務返納の熱い主張"
  },
  {
    "text": "政治家やるのも 年齢制限 必要だよな 免許返納 しないといけない年齢の人に舵取りさせたくないもんな",
    "tweet_id": "2066363291761578319",
    "url": "https://x.com/oekkdisk/status/2066363291761578319",
    "original_category": "その他・分類保留",
    "original_stance": "その他",
    "is_opinion": true,
    "stance_restriction": 1.0,
    "stance_priority": 0.5,
    "emotional_intensity": 0.5,
    "confidence": 0.7,
    "summary": "高齢政治家の年齢制限を免許返納と関連付けて支持"
  },
  {
    "text": "いい加減、運転免許の 年齢制限 は上も設けてほしい。信号機のない交差点で、こちらが優先、あっちが止まれなのに平気で出てくる老人多過ぎる。事故りそうな場面何回見てるか分からないし、老人 免許返納 しろーーーーーー！！！！！",
    "tweet_id": "2065306811285262759",
    "url": "https://x.com/ponponzoo29/status/2065306811285262759",
    "original_category": "免許返納義務化に賛成（高齢運転手の事故防止を最優先）",
    "original_stance": "義務化賛成",
    "is_opinion": true,
    "stance_restriction": 2.0,
    "stance_priority": 2.0,
    "emotional_intensity": 2.0,
    "confidence": 0.95,
    "summary": "老人ドライバーへの強い怒りと返納強制を求める怒号的投稿"
  },
  {
    "text": "#newsおかえり 個別対応したところで、 免許返納 促しても返納しないのが老人 それで小さな子供や若者の命を奪ってるんだから、もう 年齢制限 でもいいと思う 免許更新が緩すぎるのも問題！ヨボヨボの人が受かってるのとか信じられない 免許センターの人間が駄目すぎる",
    "tweet_id": "2062448624894951474",
    "url": "https://x.com/OrkCRH7kaIosFS5/status/2062448624894951474",
    "original_category": "免許返納義務化に賛成（高齢運転手の事故防止を最優先）",
    "original_stance": "義務化賛成",
    "is_opinion": true,
    "stance_restriction": 2.0,
    "stance_priority": 2.0,
    "emotional_intensity": 2.0,
    "confidence": 0.95,
    "summary": "年齢ベース返納義務化支持、強く怒り"
  },
  {
    "text": "一律での 免許返納 とかは難しい面もあると思うけど、業として運転をすることに関しては 年齢制限 を設けるべきなんでは？ https://t.co/4w837M5SlP",
    "tweet_id": "2061589539723137076",
    "url": "https://x.com/Cu_the_3rd/status/2061589539723137076",
    "original_category": "適性検査や技術的制限の強化で対応（年齢一律の義務化は避けるべき）",
    "original_stance": "適性検査強化",
    "is_opinion": true,
    "stance_restriction": 1.0,
    "stance_priority": 1.0,
    "emotional_intensity": 0.0,
    "confidence": 0.75,
    "summary": "一律返納に慎重だが職業運転に年齢制限を支持"
  },
  {
    "text": "異論反論あるだろうが、自動車免許の大型、二種などは最高 年齢制限 を設けるべきと考える。 成り手がいない？物流が死ぬ？ とか言ってる問題じゃあねぇだろ。 #自動車免許 # 免許返納",
    "tweet_id": "2061586503197979009",
    "url": "https://x.com/Andy_Moco2/status/2061586503197979009",
    "original_category": "免許返納義務化に賛成（高齢運転手の事故防止を最優先）",
    "original_stance": "義務化賛成",
    "is_opinion": true,
    "stance_restriction": 2.0,
    "stance_priority": 2.0,
    "emotional_intensity": 2.0,
    "confidence": 0.95,
    "summary": "年齢制限の法的義務化を強く支持、感情的に反対論を否定"
  },
  {
    "text": "85歳やろ？そら事故るて。なんで 免許返納 してないねん。免許 年齢制限 上限待ったなし",
    "tweet_id": "2061423994344190072",
    "url": "https://x.com/ta_ninyo/status/2061423994344190072",
    "original_category": "免許返納義務化に賛成（高齢運転手の事故防止を最優先）",
    "original_stance": "義務化賛成",
    "is_opinion": true,
    "stance_restriction": 2.0,
    "stance_priority": 2.0,
    "emotional_intensity": 2.0,
    "confidence": 0.9,
    "summary": "85歳は事故ると批判し、免許年齢上限設定を求める"
  },
  {
    "text": "轢き逃げまでして最低ぢゃのぅ!!(怒) 早く 免許返納 の 年齢制限 を法律で決めろや!! 事故の運転手、1年前に中型バスで駐車に支障　マイクロバス専従に（朝日新聞） https://t.co/PNLScoTA6T",
    "tweet_id": "2060462866944405620",
    "url": "https://x.com/toshiobeppu/status/2060462866944405620",
    "original_category": "免許返納義務化に賛成（高齢運転手の事故防止を最優先）",
    "original_stance": "義務化賛成",
    "is_opinion": true,
    "stance_restriction": 2.0,
    "stance_priority": 2.0,
    "emotional_intensity": 2.0,
    "confidence": 0.95,
    "summary": "轢き逃げ怒り、返納義務化求める"
  },
  {
    "text": "80代の運転手が30代の男女をはねるって、いい加減、 免許返納 の 年齢制限 しろや😣",
    "tweet_id": "2060355095318221196",
    "url": "https://x.com/kinta20010101/status/2060355095318221196",
    "original_category": "免許返納義務化に賛成（高齢運転手の事故防止を最優先）",
    "original_stance": "義務化賛成",
    "is_opinion": true,
    "stance_restriction": 2.0,
    "stance_priority": 2.0,
    "emotional_intensity": 2.0,
    "confidence": 0.9,
    "summary": "高齢者運転事故への怒りと返納義務化の要求"
  },
  {
    "text": "運転免許自主返納 サポート。運転に少しでも不安があれば、返納も選択の内です。 自主返納 者には、申請すると、運転経歴証明書が交付されると。僕も持っているで。高齢者による自動車事故が多発しているか。運転に少しでも不安があれば、返納も選択の内です。",
    "tweet_id": "2069378113977680275",
    "url": "https://x.com/homes9991/status/2069378113977680275",
    "original_category": "自主返納のインセンティブ強化（特典や支援）を進めるべき",
    "original_stance": "自主返納促進",
    "is_opinion": true,
    "stance_restriction": 0.0,
    "stance_priority": 0.5,
    "emotional_intensity": 0.0,
    "confidence": 0.7,
    "summary": "自主返納を促す情報投稿。個人的支持下地あり"
  },
  {
    "text": "運転免許 証 自主返納 を考えた事はないのだろうか？ https://t.co/u6ax2M8Fai",
    "tweet_id": "2066017339703992764",
    "url": "https://x.com/nanbe32058074/status/2066017339703992764",
    "original_category": "自主返納のインセンティブ強化（特典や支援）を進めるべき",
    "original_stance": "自主返納促進",
    "is_opinion": true,
    "stance_restriction": 1.0,
    "stance_priority": 1.0,
    "emotional_intensity": 0.5,
    "confidence": 0.6,
    "summary": "自主返納を促す問いかけ"
  },
  {
    "text": "運転免許 を 自主返納 するか、無効化されないといけませんね。",
    "tweet_id": "2065810429964943776",
    "url": "https://x.com/Lora6025243011/status/2065810429964943776",
    "original_category": "自主返納のインセンティブ強化（特典や支援）を進めるべき",
    "original_stance": "自主返納促進",
    "is_opinion": true,
    "stance_restriction": 1.0,
    "stance_priority": 1.0,
    "emotional_intensity": 0.0,
    "confidence": 0.6,
    "summary": "高齢者の免許自主返納・無効化を促す"
  },
  {
    "text": "運転免許 証を 自主返納 してきた もう車乗れるような動体視力やら体調やら良くなる事ないから。",
    "tweet_id": "2063812497354973568",
    "url": "https://x.com/NICORIRIS/status/2063812497354973568",
    "original_category": "自主返納のインセンティブ強化（特典や支援）を進めるべき",
    "original_stance": "自主返納促進",
    "is_opinion": true,
    "stance_restriction": -1.0,
    "stance_priority": 1.0,
    "emotional_intensity": 0.0,
    "confidence": 0.7,
    "summary": "自身は体調や視力の限界を自覚し自主返納を選択"
  },
  {
    "text": "富山県住みなのに自動車の 運転免許 を持ってない俺。気持ちが荒れた際に運転まで荒くなるので、こりゃー危ないと思って39歳当時に 自主返納 したのさー。自宅でお仕事する個人事業主なのでお仕事では使わないしね。だが昨日は釣り場までの往復でタクシー代が1万円もかかった。ちょっと痛い。",
    "tweet_id": "2063752310128583139",
    "url": "https://x.com/HonokaBoat/status/2063752310128583139",
    "original_category": "代替移動手段や公共交通機関の整備を優先すべき",
    "original_stance": "インフラ優先",
    "is_opinion": true,
    "stance_restriction": 0.0,
    "stance_priority": 0.0,
    "emotional_intensity": 0.0,
    "confidence": 0.8,
    "summary": "自主返納の体験を淡々と語る日記的投稿"
  },
  {
    "text": "運転免許 の 自主返納 で。原付のペーパードライバー５年半やって、 自主返納 と。返納した後の方が長いと。決断したと。１回更新しているけど。２回目の更新の年は、今回は、返納したいと。統合失調症か。それもあると。運転経歴証書と。原付のペーパードライバーを続ける道もあったかも知れないけど。返納",
    "tweet_id": "2063407752043782200",
    "url": "https://x.com/homes9991/status/2063407752043782200",
    "original_category": "自主返納のインセンティブ強化（特典や支援）を進めるべき",
    "original_stance": "自主返納促進",
    "is_opinion": true,
    "stance_restriction": 0.0,
    "stance_priority": 0.0,
    "emotional_intensity": 0.0,
    "confidence": 0.5,
    "summary": "自主返納の個人的経験。政策論及ばず"
  },
  {
    "text": "免許返納者であっても、生きていく以上は通院や買い物も必要だと思うのね。一次的一回限りのポイント付与ではなくて、継続的な代替交通手段や生活手段の確保が必要なんじゃないのだろうか。 滋賀県が75歳以上の 運転免許 証「 自主返納 」支援、ポイント付与が驚きの「3倍増」超に | 京都新聞デジタル",
    "tweet_id": "2062921201912263134",
    "url": "https://x.com/ayashii5/status/2062921201912263134",
    "original_category": "代替移動手段や公共交通機関の整備を優先すべき",
    "original_stance": "インフラ優先",
    "is_opinion": true,
    "stance_restriction": -1.0,
    "stance_priority": -1.5,
    "emotional_intensity": -0.5,
    "confidence": 0.85,
    "summary": "自主返納後の継続的代替交通の整備を指摘"
  },
  {
    "text": "運転免許 、 自主返納 はそのままで良きだけどやっぱ上限つけなきゃダメじゃないか？？？そもそも自分なら85で運転しようとはさすがに思わないけど",
    "tweet_id": "2061583928390230124",
    "url": "https://x.com/175175__/status/2061583928390230124",
    "original_category": "免許返納義務化に賛成（高齢運転手の事故防止を最優先）",
    "original_stance": "義務化賛成",
    "is_opinion": true,
    "stance_restriction": 1.0,
    "stance_priority": 0.5,
    "emotional_intensity": 0.5,
    "confidence": 0.75,
    "summary": "自主返納は維持しつつも年齢上限設定を支持"
  },
  {
    "text": "これで85歳か… 運転免許 の 自主返納 ってやっぱりもっと進まないと厳しいよね💦",
    "tweet_id": "2060945922465599639",
    "url": "https://x.com/KimResearch_/status/2060945922465599639",
    "original_category": "自主返納のインセンティブ強化（特典や支援）を進めるべき",
    "original_stance": "義務化反対",
    "is_opinion": true,
    "stance_restriction": -1.0,
    "stance_priority": -1.0,
    "emotional_intensity": -1.0,
    "confidence": 0.6,
    "summary": "自主返納不进む現状への嘆きと軽い諦め"
  },
  {
    "text": "高齢ドライバー の「運転技能検査」見直しへ　合格者の 事故 率高く(毎日新聞) #Yahooニュース https://t.co/dwwUKIqfAn 対策 は必要だけど高齢者が多い地域ほど車社会なんだよね。車が無いと生活できないんだ。取り締まりを強める前に移動をカバーする施策を整備するべきなんだよ。",
    "tweet_id": "2070273120079138901",
    "url": "https://x.com/hoho_desu/status/2070273120079138901",
    "original_category": "代替移動手段や公共交通機関の整備を優先すべき",
    "original_stance": "インフラ優先",
    "is_opinion": true,
    "stance_restriction": -1.0,
    "stance_priority": -1.0,
    "emotional_intensity": 0.0,
    "confidence": 0.8,
    "summary": "移動手段の整備を先行させるべきとの意見"
  },
  {
    "text": "高齢ドライバー の逆走、こうした 事故 がなぜ起きるのか改めて考えさせられます。安全 対策 の強化が急務だと感じます。",
    "tweet_id": "2070155758424269285",
    "url": "https://x.com/chama5714/status/2070155758424269285",
    "original_category": "適性検査や技術的制限の強化で対応（年齢一律の義務化は避けるべき）",
    "original_stance": "適性検査強化",
    "is_opinion": true,
    "stance_restriction": 0.0,
    "stance_priority": 0.0,
    "emotional_intensity": 0.0,
    "confidence": 0.6,
    "summary": "安全対策強化を願う穏当な意見、立場不明"
  },
  {
    "text": "高齢ドライバー の安全 対策 はとても重要ですね。 調査結果を踏まえた実車試験の見直し検討、 事故 を減らす良い機会になると思います。 皆さんが安心して道路を利用できる社会になることを願っています。",
    "tweet_id": "2070125427600044378",
    "url": "https://x.com/Blackhole260685/status/2070125427600044378",
    "original_category": "適性検査や技術的制限の強化で対応（年齢一律の義務化は避けるべき）",
    "original_stance": "適性検査強化",
    "is_opinion": true,
    "stance_restriction": 0.0,
    "stance_priority": 0.5,
    "emotional_intensity": 0.0,
    "confidence": 0.6,
    "summary": "安全対策重要と認めつつも強制には言及せず"
  },
  {
    "text": "高齢ドライバー の安全 対策 はとても重要ですね。 事故 率が2倍以上というのは深刻です。 実車試験の見直しを早急に進めて、 皆が安心して道路を使える環境になることを願っています。",
    "tweet_id": "2070116967902593367",
    "url": "https://x.com/Salamison/status/2070116967902593367",
    "original_category": "適性検査や技術的制限の強化で対応（年齢一律の義務化は避けるべき）",
    "original_stance": "適性検査強化",
    "is_opinion": true,
    "stance_restriction": 0.5,
    "stance_priority": 1.0,
    "emotional_intensity": 0.0,
    "confidence": 0.75,
    "summary": "高齢者の安全対策を重要視し、実車試験の見直しを願っている"
  },
  {
    "text": "高齢ドライバー の「運転技能検査」見直しへ　合格者の 事故 率高く(毎日新聞) ようやく高齢者 対策 がとられたね よく読むとわかるけど、違反しなければめんどくさいことはない 違反するような不適切運転をする高齢者の 事故 が多いからこうなっただけ #Yahooニュース https://t.co/xo2FfZOCjh",
    "tweet_id": "2070036693953261575",
    "url": "https://x.com/35vC43KbqwKDwe6/status/2070036693953261575",
    "original_category": "適性検査や技術的制限の強化で対応（年齢一律の義務化は避けるべき）",
    "original_stance": "適性検査強化",
    "is_opinion": true,
    "stance_restriction": 1.0,
    "stance_priority": 1.0,
    "emotional_intensity": 0.0,
    "confidence": 0.6,
    "summary": "高齢者対策支持。違反による事故防止を正当化"
  },
  {
    "text": "運転技能検査は「免許を更新できるか」の入口として重要ですが、合格者の 事故 率が高いのであれば、制度設計の見直しは不可避だと思います。 高齢ドライバー対策 は、単に年齢で線引きするのではなく、認知機能・運転技能・生活圏の移動手段をセットで考える必要… #NewsPicks https://t.co/fGd2gtMNvO",
    "tweet_id": "2070023912885559385",
    "url": "https://x.com/Masaya02909344/status/2070023912885559385",
    "original_category": "適性検査や技術的制限の強化で対応（年齢一律の義務化は避けるべき）",
    "original_stance": "適性検査強化",
    "is_opinion": true,
    "stance_restriction": -1.0,
    "stance_priority": -1.0,
    "emotional_intensity": 0.5,
    "confidence": 0.7,
    "summary": "年齢線引きに慎重な立場から包括的な制度設計を主張"
  },
  {
    "text": "高齢ドライバー の踏み間違いは確かに重大な 事故 につながることがありますが、一概に年齢だけの問題ではなく、誰にでも起こり得ることだと思います。運転支援システムの普及や定期的な運転確認など、安全 対策 を強化していくことが大切ですね。",
    "tweet_id": "2069065587612143849",
    "url": "https://x.com/Ishaqsafdar76/status/2069065587612143849",
    "original_category": "適性検査や技術的制限の強化で対応（年齢一律の義務化は避けるべき）",
    "original_stance": "適性検査強化",
    "is_opinion": true,
    "stance_restriction": -1.0,
    "stance_priority": -1.0,
    "emotional_intensity": 0.0,
    "confidence": 0.8,
    "summary": "踏み間違いは年齢だけでなく誰にでも起き得るとし、技術導入や安全対策を重視する冷静な意見"
  },
  {
    "text": "高齢ドライバー の操作ミスは重大 事故 につながるので、免許制度や安全 対策 の強化が重要だと思います。",
    "tweet_id": "2069049461377298903",
    "url": "https://x.com/iam_blackcat/status/2069049461377298903",
    "original_category": "適性検査や技術的制限の強化で対応（年齢一律の義務化は避けるべき）",
    "original_stance": "適性検査強化",
    "is_opinion": true,
    "stance_restriction": 1.0,
    "stance_priority": 1.0,
    "emotional_intensity": 0.0,
    "confidence": 0.7,
    "summary": "安全対策強化を支持する冷静な意見"
  },
  {
    "text": "重大 事故 でも被害を最小限に抑えられたのは、チャイルドシートの設計と正しい使用が機能した結果だと思う。一方で 高齢ドライバー の安全運転 対策 も含め、交通 事故 全体の構造的課題は依然として大きい。",
    "tweet_id": "2067246164358132118",
    "url": "https://x.com/MJA_669/status/2067246164358132118",
    "original_category": "適性検査や技術的制限の強化で対応（年齢一律の義務化は避けるべき）",
    "original_stance": "適性検査強化",
    "is_opinion": true,
    "stance_restriction": 0.0,
    "stance_priority": 0.0,
    "emotional_intensity": 0.0,
    "confidence": 0.6,
    "summary": "返納強制・移動権に言及せず中立分析"
  },
  {
    "text": "高齢ドライバー の 事故 ってなぜ無くならない？ホントにイライラする。マジで駆逐してやりたい。高市さん、マジで 対策 頼みますよ？国がやらないなら自分たちでどうにかしないと。後先無い老人が若者を轢き殺すこの現状に何とも思わない日本国は腐っている。 # 高齢ドライバー #85歳ドライバー #老害",
    "tweet_id": "2061555622848647195",
    "url": "https://x.com/lucky7hrs4u/status/2061555622848647195",
    "original_category": "免許返納義務化に賛成（高齢運転手の事故防止を最優先）",
    "original_stance": "義務化賛成",
    "is_opinion": true,
    "stance_restriction": 2.0,
    "stance_priority": 2.0,
    "emotional_intensity": 2.0,
    "confidence": 0.95,
    "summary": "高齢者の強制返納求める強い批判的意見"
  },
  {
    "text": "→85歳の 高齢ドライバー が悪いような報道が多い気がするけど、85歳を送迎ドライバーとして雇っていた企業の罪はもっと重いと思う。いい加減にこのような不幸な 事故 が無くなる 対策 を本気で進めてほしい。 https://t.co/KcaSuMb4rj",
    "tweet_id": "2061454190220853573",
    "url": "https://x.com/Shohei_TAKEDA1/status/2061454190220853573",
    "original_category": "適性検査や技術的制限の強化で対応（年齢一律の義務化は避けるべき）",
    "original_stance": "適性検査強化",
    "is_opinion": true,
    "stance_restriction": 0.0,
    "stance_priority": 1.5,
    "emotional_intensity": 1.0,
    "confidence": 0.7,
    "summary": "企業の雇用責任追及と事故防止策の実行を主張"
  },
  {
    "text": "車を利用しないと不便な 地方 に住んでいます。運転免許証の返納は 生活 不能＝死です。買物にも病院にも散髪にすら行けません。公共交通機関のバスでは満足な移動はできません。市内移動はできてもそれ以上には行けないのです。 免許返納 時には安楽死尊厳死を希望します。 #国は安楽死を認めてください",
    "tweet_id": "2070818858425020700",
    "url": "https://x.com/new_yamanjy_thd/status/2070818858425020700",
    "original_category": "免許返納義務化に反対（地方の生活維持や移動手段確保を重視）",
    "original_stance": "義務化反対",
    "is_opinion": true,
    "stance_restriction": -2.0,
    "stance_priority": -2.0,
    "emotional_intensity": 2.0,
    "confidence": 0.85,
    "summary": "地方在住者の移動権重視と返納反対の感情的な意見"
  },
  {
    "text": "高齢者の 免許返納 拒否、よくわかる話だね。 地方 のバスが1日2本じゃ 生活 できないよ。交通網をちゃんと整備しない限り、この問題はなくならない。",
    "tweet_id": "2070003983486484494",
    "url": "https://x.com/phraephannita/status/2070003983486484494",
    "original_category": "免許返納義務化に反対（地方の生活維持や移動手段確保を重視）",
    "original_stance": "義務化反対",
    "is_opinion": true,
    "stance_restriction": -1.0,
    "stance_priority": -1.0,
    "emotional_intensity": -1.0,
    "confidence": 0.85,
    "summary": "地方交通の未整備を指摘し、返納強制には慎重な意見"
  },
  {
    "text": "厳格化してガンガン取り上げろ 別に合格すりゃ問題ないんだから、 免許返納 後の 生活 を保障しろとか文句言ってるマヌケは無視で そもそも資格がないのに乗ってるのがおかしいんだから、自信ないなら若いうちに 地方 出ろよ https://t.co/fG45ZFFrZd",
    "tweet_id": "2069975357151994271",
    "url": "https://x.com/resba_referee/status/2069975357151994271",
    "original_category": "免許返納義務化に賛成（高齢運転手の事故防止を最優先）",
    "original_stance": "義務化賛成",
    "is_opinion": true,
    "stance_restriction": 1.5,
    "stance_priority": 1.5,
    "emotional_intensity": 2.0,
    "confidence": 0.85,
    "summary": "厳格化支持・批判的で感情的"
  },
  {
    "text": "『返納したら 生活 できない』 地方 ほど切実ですよね…！実は 免許返納 すると『運転経歴証明書』がもらえて、自治体によってはタクシー券やコミュニティバスの割引、預金金利の上乗せなどの特典が受けられるんですよね。返納前に市役所の窓口で対象特典を一覧でもらっておくと損しないですよね🤝",
    "tweet_id": "2069896952230379612",
    "url": "https://x.com/rupauni508/status/2069896952230379612",
    "original_category": "自主返納のインセンティブ強化（特典や支援）を進めるべき",
    "original_stance": "自主返納促進",
    "is_opinion": true,
    "stance_restriction": -1.0,
    "stance_priority": -1.0,
    "emotional_intensity": 0.5,
    "confidence": 0.7,
    "summary": "地方の実情に共感しつつ、返納特典の情報を案内する投稿"
  },
  {
    "text": "病院の駐車場ではねられる 死亡 #Yahooニュース https://t.co/itvlD3SUfg 車の事故が多すぎる…車社会から脱却すべき‼️ 地方 では車ないと 生活 できないが…交通手段がある都市部は 免許返納 した方が良い",
    "tweet_id": "2068338361849577558",
    "url": "https://x.com/rinrintoyochan/status/2068338361849577558",
    "original_category": "免許返納義務化に反対（地方の生活維持や移動手段確保を重視）",
    "original_stance": "義務化反対",
    "is_opinion": true,
    "stance_restriction": 0.5,
    "stance_priority": 0.5,
    "emotional_intensity": 0.5,
    "confidence": 0.8,
    "summary": "事故への怒りと車依存社会への疑問"
  },
  {
    "text": "車を利用しないと不便な 地方 に住んでいます。運転免許証の返納は 生活 不能＝死です。買物にも病院にも散髪にすら行けません。公共交通機関のバスでは満足な移動はできません。市内移動はできてもそれ以上には行けないのです。 免許返納 時には安楽死尊厳死を希望します。 #国は安楽死を認めてください",
    "tweet_id": "2068281057674399848",
    "url": "https://x.com/new_yamanjy_thd/status/2068281057674399848",
    "original_category": "免許返納義務化に反対（地方の生活維持や移動手段確保を重視）",
    "original_stance": "義務化反対",
    "is_opinion": true,
    "stance_restriction": -2.0,
    "stance_priority": -2.0,
    "emotional_intensity": 2.0,
    "confidence": 0.9,
    "summary": "地方在住者が返納強度に強く反対し移動権最優先で感情的な意見を述べた"
  },
  {
    "text": "免許返納 は本当に難しいよね。 地方 はクルマが 生活 の必需品になってるしね…。",
    "tweet_id": "2066661714008146366",
    "url": "https://x.com/V5K8r/status/2066661714008146366",
    "original_category": "免許返納義務化に反対（地方の生活維持や移動手段確保を重視）",
    "original_stance": "義務化反対",
    "is_opinion": true,
    "stance_restriction": -1.0,
    "stance_priority": -2.0,
    "emotional_intensity": 0.0,
    "confidence": 0.7,
    "summary": "地方の実情を考虑し返納难了を示す共感投稿"
  },
  {
    "text": "高齢になったら「 免許返納 を考える事」は回りの人を守る為だけでなく、自分を守る為でもあるとの考えが広がって欲しい 車を運転しなくても 生活 できる街作りや仕組みも必要です (自分も 地方 の人間なので車がなければ 生活 できない状況は知っています)",
    "tweet_id": "2066501067366621318",
    "url": "https://x.com/kouji20221/status/2066501067366621318",
    "original_category": "免許返納義務化に賛成（高齢運転手の事故防止を最優先）",
    "original_stance": "義務化賛成",
    "is_opinion": true,
    "stance_restriction": -1.0,
    "stance_priority": 0.0,
    "emotional_intensity": 0.0,
    "confidence": 0.7,
    "summary": "高齢者自主的な返納促進と街作り整備の提唱"
  },
  {
    "text": "わたしは恐怖の裏返しから敵意むきだしの眼差しをおじいちゃんに向けてしまったのですが、 わたしを轢きかけたことに気づいてからも、目の焦点が合っていない印象でした🥲 地方 は車がないと 生活 が成り立たない事情があり、 免許返納 しづらいですよね...",
    "tweet_id": "2065327314393833499",
    "url": "https://x.com/shimakaze33/status/2065327314393833499",
    "original_category": "免許返納義務化に反対（地方の生活維持や移動手段確保を重視）",
    "original_stance": "義務化反対",
    "is_opinion": true,
    "stance_restriction": -1.0,
    "stance_priority": -1.0,
    "emotional_intensity": -0.5,
    "confidence": 0.7,
    "summary": "高齢者視点の共感的振り返り。返納強制に慎重な立場"
  },
  {
    "text": "そんな父親も70代半ばで、 免許返納 してましたが、23区内だと、それでも普段の 生活 に不便は感じないし、実際自分も車は運転出来ないのですが、少し郊外行くと車無いと 生活 出来ないもんなぁ…。 軍事だとかリニアだとかなんかより、 地方 でも自動運転等で、年取ったり免許無くても",
    "tweet_id": "2065055896422797363",
    "url": "https://x.com/kaedenomoritomi/status/2065055896422797363",
    "original_category": "免許返納義務化に反対（地方の生活維持や移動手段確保を重視）",
    "original_stance": "義務化反対",
    "is_opinion": true,
    "stance_restriction": 0.0,
    "stance_priority": -1.0,
    "emotional_intensity": 0.0,
    "confidence": 0.8,
    "summary": "父親返納体験語り地方と都市の車必要性違い指摘"
  },
  {
    "text": "遭遇するのではないかと通る度緊張感が💦 地方 だと車なしでは 生活 できないから 免許返納 したくてもできないだろうから切ないね。こんな社会になることは何十年も前から分かっていたのに、インフラ整備も進まぬまま。 日本は先延ばしにしてきた問題が多過ぎ（日本ほど自動運転が必要な国他にある？）🥲",
    "tweet_id": "2064824596160004587",
    "url": "https://x.com/ikeamam/status/2064824596160004587",
    "original_category": "代替移動手段や公共交通機関の整備を優先すべき",
    "original_stance": "インフラ優先",
    "is_opinion": true,
    "stance_restriction": -1.0,
    "stance_priority": -1.0,
    "emotional_intensity": -1.0,
    "confidence": 0.8,
    "summary": "地方高齢者の切実な状況に同情し社会問題放置を嘆く"
  },
  {
    "text": "トヨタが自動運転のティアフォーへ10億円出資⁉️ 地方 では運転手不足が深刻。 自動運転は「便利」じゃなくて「 生活 の足を守る」技術！ 両親もそろそろ 免許返納 しなきゃダメな年齢。はやく技術が進んで欲しい🥺 https://t.co/L823okezft",
    "tweet_id": "2064471684116349407",
    "url": "https://x.com/taiyokomori_SRC/status/2064471684116349407",
    "original_category": "適性検査や技術的制限の強化で対応（年齢一律の義務化は避けるべき）",
    "original_stance": "適性検査強化",
    "is_opinion": true,
    "stance_restriction": -0.5,
    "stance_priority": -1.0,
    "emotional_intensity": 0.5,
    "confidence": 0.7,
    "summary": "技術が普及すれば自然に返納できるとの消極的賛成"
  },
  {
    "text": "高齢者ならば 免許返納 推奨したいけども、 地方 は車社会だから車ないと 生活 できないし難しいそう 無人で動くタクシーみたいなのとかが日本にもあればいいのにねぇ https://t.co/QVFxw8FEs4",
    "tweet_id": "2063598686186389950",
    "url": "https://x.com/kankan_99810000/status/2063598686186389950",
    "original_category": "代替移動手段や公共交通機関の整備を優先すべき",
    "original_stance": "インフラ優先",
    "is_opinion": true,
    "stance_restriction": -1.0,
    "stance_priority": -1.0,
    "emotional_intensity": 0.0,
    "confidence": 0.7,
    "summary": "返納推奨だが地方事情考慮すべきとの慎重な意見"
  },
  {
    "text": "車を利用しないと不便な 地方 に住んでいます。運転免許証の返納は 生活 不能＝死です。買物にも病院にも散髪にすら行けません。公共交通機関のバスでは満足な移動はできません。市内移動はできてもそれ以上には行けないのです。 免許返納 時には安楽死尊厳死を希望します。 #国は安楽死を認めてください",
    "tweet_id": "2063208587544158384",
    "url": "https://x.com/new_yamanjy_thd/status/2063208587544158384",
    "original_category": "免許返納義務化に反対（地方の生活維持や移動手段確保を重視）",
    "original_stance": "義務化反対",
    "is_opinion": true,
    "stance_restriction": -2.0,
    "stance_priority": -2.0,
    "emotional_intensity": 2.0,
    "confidence": 0.95,
    "summary": "地方在住者が返納すれば生活不能と強く主張"
  },
  {
    "text": "「親が高齢で運転が心配…」 でも、 地方 だから車がないと 生活 できない🫨 ピタクルは 免許返納 で 中途解約金が免除される。 オリコで乗ーるにも 免許返納 オプションがある。 親のカーリース選び、は、 「辞めやすさ」で選ぶ時代なのかも👌",
    "tweet_id": "2063075548985962967",
    "url": "https://x.com/Paroncarlease/status/2063075548985962967",
    "original_category": "免許返納義務化に反対（地方の生活維持や移動手段確保を重視）",
    "original_stance": "義務化反対",
    "is_opinion": true,
    "stance_restriction": -1.0,
    "stance_priority": 0.0,
    "emotional_intensity": 0.5,
    "confidence": 0.75,
    "summary": "返納しやすい制度設計を推奨、地方の移動問題も認識"
  },
  {
    "text": "「ママには内緒だよ🤫」 って母が娘ちゃんに言ったらしい 内容は “また車を運転する”宣言🚗 いやいや、母よ その相手 心の声も秘密も 全部ダダ漏れする家系です😂 数分後には しっかり私の耳に でも 地方 では 車＝足 免許返納 は 運転をやめることじゃなくて 今まで出来ていた 生活 を手放すこと",
    "tweet_id": "2063054898485432525",
    "url": "https://x.com/nonevvo/status/2063054898485432525",
    "original_category": "免許返納義務化に反対（地方の生活維持や移動手段確保を重視）",
    "original_stance": "義務化反対",
    "is_opinion": true,
    "stance_restriction": -1.5,
    "stance_priority": -2.0,
    "emotional_intensity": -1.0,
    "confidence": 0.85,
    "summary": "地方高齢者の生活手段として車の重要性を指摘"
  },
  {
    "text": "地方 で高齢者が 免許返納 出来ない理由... 生活 に支障をきたす　🏥や買い物が困るからかな、タクシー🚕使って🙏って思ってたけど、なんとゴミ捨て場が減っていて特に資源ゴミの回収が若い人だって歩きたくない距離の所に変更されてた　自治体、政府！こういう所に目を向けてそういう事に税金使って❗️",
    "tweet_id": "2062736909122884008",
    "url": "https://x.com/angelsnow04/status/2062736909122884008",
    "original_category": "代替移動手段や公共交通機関の整備を優先すべき",
    "original_stance": "義務化反対",
    "is_opinion": true,
    "stance_restriction": -1.5,
    "stance_priority": -2.0,
    "emotional_intensity": 1.0,
    "confidence": 0.8,
    "summary": "地方高齢者、返納困難で生活困窮と支援不足を訴求"
  },
  {
    "text": "地方 は、車長いと 生活 できない。 タクシーは呼んでもこない。 免許返納 も大事だけど、 免許返納 が進むまちづくりも大事だよね。 だって、これから皆高齢者になっていくんだもん。 https://t.co/VTqqJAxwww",
    "tweet_id": "2060692752636199174",
    "url": "https://x.com/AnnarizuA/status/2060692752636199174",
    "original_category": "免許返納義務化に反対（地方の生活維持や移動手段確保を重視）",
    "original_stance": "義務化反対",
    "is_opinion": true,
    "stance_restriction": -1.0,
    "stance_priority": -1.5,
    "emotional_intensity": 0.0,
    "confidence": 0.7,
    "summary": "移動権を重視し強制返納に慎重な姿勢、地方の現実も考慮"
  },
  {
    "text": "車を利用しないと不便な 地方 に住んでいます。運転免許証の返納は 生活 不能＝死です。買物にも病院にも散髪にすら行けません。公共交通機関のバスでは満足な移動はできません。市内移動はできてもそれ以上には行けないのです。 免許返納 時には安楽死尊厳死を希望します。 #国は安楽死を認めてください",
    "tweet_id": "2060669013341229424",
    "url": "https://x.com/new_yamanjy_thd/status/2060669013341229424",
    "original_category": "免許返納義務化に反対（地方の生活維持や移動手段確保を重視）",
    "original_stance": "義務化反対",
    "is_opinion": true,
    "stance_restriction": -2.0,
    "stance_priority": -2.0,
    "emotional_intensity": 2.0,
    "confidence": 0.95,
    "summary": "地方在住者が返納強制に強く反対し移動権優先の立場"
  },
  {
    "text": "日本の国土の約7割は山間部。そこで暮らす人の多くは高齢者。高齢者ドライバーの事故が起きるたびに 免許返納 をさせろとか話題なるけど、山間部の車は 生活 インフラ。もし 免許返納 を進めれば、 生活 できなくなり、 地方 そのものが成り立たなくなる。かと言って死者は悲劇で、この問題は、難しいよな。",
    "tweet_id": "2060548569606840704",
    "url": "https://x.com/mossusan/status/2060548569606840704",
    "original_category": "免許返納義務化に反対（地方の生活維持や移動手段確保を重視）",
    "original_stance": "義務化反対",
    "is_opinion": true,
    "stance_restriction": -1.0,
    "stance_priority": -1.0,
    "emotional_intensity": 0.0,
    "confidence": 0.8,
    "summary": "山間部の車は生活インフラで、返納強制は地方壊す"
  },
  {
    "text": "高齢者 の 運転 技能検査 見直しへ https://t.co/PHUmWW2qi0 違反よりも、「事故ややらかし」を参考にした方がいい気がする。 運転 をやめさせたい家族、仕事柄「 やめろ 」なんて言えない修理業者など、技能検査では測れない要素がある。 運転 をやめさせても問題ないだけの社会的受け皿も必要だが。",
    "tweet_id": "2070013060744704490",
    "url": "https://x.com/MikuLarenGt_r/status/2070013060744704490",
    "original_category": "適性検査や技術的制限の強化で対応（年齢一律の義務化は避けるべき）",
    "original_stance": "適性検査強化",
    "is_opinion": true,
    "stance_restriction": -1.0,
    "stance_priority": -1.0,
    "emotional_intensity": 0.0,
    "confidence": 0.85,
    "summary": "技能検査の限界と社会的受け皿の必要性"
  },
  {
    "text": "30秒くらいから歩道も無いような道で暴走。タクシーも おかしい が撮影者も相当危険運転。タクシーから逃れるためかもしれんが歩行者自転車を危険に晒す行為。どちらの運転者も 免許返納 を勧める。 https://t.co/OpPwmMN4Fb",
    "tweet_id": "2070109565195370851",
    "url": "https://x.com/jianzijun381019/status/2070109565195370851",
    "original_category": "免許返納義務化に賛成（高齢運転手の事故防止を最優先）",
    "original_stance": "義務化賛成",
    "is_opinion": true,
    "stance_restriction": 1.0,
    "stance_priority": 1.0,
    "emotional_intensity": 1.0,
    "confidence": 0.8,
    "summary": "危険運転の動画を見て双方に返納を促す意見"
  },
  {
    "text": "新発田の運転手まじで運転技術マナークソボケっとしすぎとろすぎ青信号セパレート何もないのや字も読めないクソ化け物共がいっちょ前に普通の車運転してんな無理だわ馬鹿のろまボケ下手くそ共馬鹿全て軽トラ乗るか 免許返納 しろ頭 おかしい クソ化け物共ばかりわきやがって目ついてんの状況見ろボケ共◯ね",
    "tweet_id": "2069966305705480367",
    "url": "https://x.com/catcat2921/status/2069966305705480367",
    "original_category": "免許返納義務化に賛成（高齢運転手の事故防止を最優先）",
    "original_stance": "義務化賛成",
    "is_opinion": true,
    "stance_restriction": 2.0,
    "stance_priority": 2.0,
    "emotional_intensity": 2.0,
    "confidence": 0.85,
    "summary": "危険運転への激怒と返納強制を主張する怒りの投稿"
  },
  {
    "text": "クイズともしげ本物の怖さと笑いが共存してて見応えあった みなみかわ家のためにも 免許返納 してほしいけど修理代出すって罰ゲーム おかしい wwww",
    "tweet_id": "2069955495520325711",
    "url": "https://x.com/cynicalpink_/status/2069955495520325711",
    "original_category": "免許返納義務化に反対（地方の生活維持や移動手段確保を重視）",
    "original_stance": "義務化反対",
    "is_opinion": true,
    "stance_restriction": 0.5,
    "stance_priority": 0.0,
    "emotional_intensity": 0.5,
    "confidence": 0.4,
    "summary": "クイズ番組感想とみなみかわ絡みのlicense返納冗談"
  },
  {
    "text": "これで責任感じないなら 免許返納 しろ。 こんな視界狭い、認知が おかしい 状態で運転なんかするな。本当に意味がわからない https://t.co/39CVyUsWPt",
    "tweet_id": "2068997186512363938",
    "url": "https://x.com/kamekametroop/status/2068997186512363938",
    "original_category": "免許返納義務化に賛成（高齢運転手の事故防止を最優先）",
    "original_stance": "義務化賛成",
    "is_opinion": true,
    "stance_restriction": 2.0,
    "stance_priority": 2.0,
    "emotional_intensity": 2.0,
    "confidence": 0.9,
    "summary": "高齢者運転に激怒し法的返納求める意見"
  },
  {
    "text": "出庫待ちして歩道を塞いでいるのに左右確認もなく動いて事故 自転車が被害者 この歩道自転車歩道走行可だし13歳以下と75歳以上はそもそも歩道通行可です 歩道に逆走はないので逆走の主張も おかしい 大阪でこの運転してよく今まで事故しなかったね これで被害者意識があるならもう 免許返納 してほしい",
    "tweet_id": "2068989076104204687",
    "url": "https://x.com/33uramisis/status/2068989076104204687",
    "original_category": "免許返納義務化に反対（地方の生活維持や移動手段確保を重視）",
    "original_stance": "義務化反対",
    "is_opinion": true,
    "stance_restriction": 1.5,
    "stance_priority": 1.0,
    "emotional_intensity": 1.5,
    "confidence": 0.85,
    "summary": "大阪での事故、加害者が被害者意識なら返納すべき"
  },
  {
    "text": "ハザード出せばいいと思ってるやつガチで頭 おかしい よ ありえないタイミングで割り込みしてきてお前らみたいなやつのせいで事故起こるんだよ 免許返納 したらいかが？",
    "tweet_id": "2068821692865294660",
    "url": "https://x.com/rnz_xx0/status/2068821692865294660",
    "original_category": "免許返納義務化に賛成（高齢運転手の事故防止を最優先）",
    "original_stance": "義務化賛成",
    "is_opinion": true,
    "stance_restriction": 1.0,
    "stance_priority": 2.0,
    "emotional_intensity": 2.0,
    "confidence": 0.85,
    "summary": "危険な割り込み司机に怒り、返納を促す意見"
  },
  {
    "text": "免許返納 表明してる山中湖にバス放流すんの おかしい だろ。 河口湖にしろよ。",
    "tweet_id": "2068660066673430853",
    "url": "https://x.com/shinamonkukki/status/2068660066673430853",
    "original_category": "免許返納義務化に反対（地方の生活維持や移動手段確保を重視）",
    "original_stance": "義務化反対",
    "is_opinion": true,
    "stance_restriction": 0.0,
    "stance_priority": 0.0,
    "emotional_intensity": 1.0,
    "confidence": 0.5,
    "summary": "山中湖へのバス運行に疑問を呈する個人的意見"
  },
  {
    "text": "逆走車も、何か おかしい と思って停車するならまだしも、走り続ける時点で認識力の低下が起きてるから、即 免許返納 で良い位だね。 https://t.co/1u0F17P6wB",
    "tweet_id": "2068163647952884054",
    "url": "https://x.com/super_cubo/status/2068163647952884054",
    "original_category": "免許返納義務化に賛成（高齢運転手の事故防止を最優先）",
    "original_stance": "義務化賛成",
    "is_opinion": true,
    "stance_restriction": 2.0,
    "stance_priority": 2.0,
    "emotional_intensity": 1.0,
    "confidence": 0.85,
    "summary": "逆走続ける高齢者の即返納を主張"
  },
  {
    "text": "ボーっとしてここまで侵入を許してるかっぱ警備員もおかしければ、ただ見てるだけで料金払って降りてく客も おかしい 。これがタクシー運転手だというのが一番 おかしい が。#タクシー　# 免許返納 https://t.co/RnPbsTWrgw",
    "tweet_id": "2068163535105081760",
    "url": "https://x.com/New4141105/status/2068163535105081760",
    "original_category": "免許返納義務化に賛成（高齢運転手の事故防止を最優先）",
    "original_stance": "義務化賛成",
    "is_opinion": true,
    "stance_restriction": 0.5,
    "stance_priority": 1.0,
    "emotional_intensity": 1.5,
    "confidence": 0.65,
    "summary": "タクシー運転手の行動への批判と不安全状況への怒り"
  },
  {
    "text": "一部の国道で速度超過で流れてるのが常態化しているからって制限速度を守ってる方が危険因子って公言して憚らない人は頭の作りが おかしい ので 免許返納 して欲しい。他責にするなよ。「速度超過を自覚しているので、それで先行車に追突したら自分の責任ですね、気をつけます」位言ってのけろ",
    "tweet_id": "2068126258182189518",
    "url": "https://x.com/TNaka2011/status/2068126258182189518",
    "original_category": "免許返納義務化に賛成（高齢運転手の事故防止を最優先）",
    "original_stance": "義務化賛成",
    "is_opinion": true,
    "stance_restriction": 1.5,
    "stance_priority": 1.5,
    "emotional_intensity": 1.5,
    "confidence": 0.85,
    "summary": "速度超過の言い訳する人にlicense返納促す"
  },
  {
    "text": "本当それ、止まれの標識あって、下に止まれのマークもあるのに止まらない方が おかしい 。これは 免許返納 レベル https://t.co/yQSVlWiUeb",
    "tweet_id": "2068102500050505773",
    "url": "https://x.com/kibunya_2ken/status/2068102500050505773",
    "original_category": "免許返納義務化に賛成（高齢運転手の事故防止を最優先）",
    "original_stance": "義務化賛成",
    "is_opinion": true,
    "stance_restriction": 1.0,
    "stance_priority": 1.5,
    "emotional_intensity": 1.0,
    "confidence": 0.75,
    "summary": "止まれない行為に強く批判、高龄者の返納を支持"
  },
  {
    "text": "頭の おかしい 君は必ず事故するから 免許返納 しろよ(^ω^)病気の奴が運転してたら命がいくつあっても足りないからな、犯罪者になる前に運転やめろよゴミカス(*^^*)",
    "tweet_id": "2067910293192380518",
    "url": "https://x.com/MODMAD_is_wuss/status/2067910293192380518",
    "original_category": "免許返納義務化に賛成（高齢運転手の事故防止を最優先）",
    "original_stance": "義務化賛成",
    "is_opinion": true,
    "stance_restriction": 2.0,
    "stance_priority": 2.0,
    "emotional_intensity": 2.0,
    "confidence": 0.95,
    "summary": "極めて強い怒りと侮蔑で返納強制・安全最優先を主張"
  },
  {
    "text": "右車線から左折するクソジジイに遭遇してブチギレた😂頭 おかしい んちゃん😂 免許返納 してくれ頼む🙏",
    "tweet_id": "2067816842866102547",
    "url": "https://x.com/_thr0605/status/2067816842866102547",
    "original_category": "免許返納義務化に賛成（高齢運転手の事故防止を最優先）",
    "original_stance": "義務化賛成",
    "is_opinion": true,
    "stance_restriction": 1.0,
    "stance_priority": 1.0,
    "emotional_intensity": 2.0,
    "confidence": 0.85,
    "summary": "高齢ドライバーの危険運転への激怒と返納要求"
  },
  {
    "text": "制限速度30のところ30キロで走ってて捕まるってどんな状況？言ってて おかしい ことに気づかないんだろうか。早く 免許返納 してほしい。",
    "tweet_id": "2067736921787531770",
    "url": "https://x.com/dRTPUnwE03lGZt4/status/2067736921787531770",
    "original_category": "免許返納義務化に賛成（高齢運転手の事故防止を最優先）",
    "original_stance": "義務化賛成",
    "is_opinion": true,
    "stance_restriction": 2.0,
    "stance_priority": 2.0,
    "emotional_intensity": 2.0,
    "confidence": 0.85,
    "summary": "速度超過の不安全運転を批判し高齢者へ返納促す"
  },
  {
    "text": "頭 おかしい 免許返納 しろ 警察官の指示や緊急車両を除き直進車優先だ どこの国の人なの？ https://t.co/2cJqt5vuLq",
    "tweet_id": "2067422686452879745",
    "url": "https://x.com/mara2020zx/status/2067422686452879745",
    "original_category": "免許返納義務化に賛成（高齢運転手の事故防止を最優先）",
    "original_stance": "義務化賛成",
    "is_opinion": true,
    "stance_restriction": 1.0,
    "stance_priority": 2.0,
    "emotional_intensity": 2.0,
    "confidence": 0.95,
    "summary": "高齢者の免許返納を強制的に促す、安全最優先の怒りの投稿"
  },
  {
    "text": "60キロ同士と50キロ同士の事故が、変わらない訳ないだろ、あたま おかしい なほんま、こんなバカは相手にするだけ無駄だったわ、事故起こして他人様に迷惑をかける前に 免許返納 しろよ、お願いだから",
    "tweet_id": "2067200923433353283",
    "url": "https://x.com/Katsu_Pawn/status/2067200923433353283",
    "original_category": "免許返納義務化に賛成（高齢運転手の事故防止を最優先）",
    "original_stance": "義務化賛成",
    "is_opinion": true,
    "stance_restriction": 1.5,
    "stance_priority": 1.5,
    "emotional_intensity": 1.5,
    "confidence": 0.8,
    "summary": "怒り・高齢者返納求める・事故への不満"
  },
  {
    "text": "左に中央分離帯があって、その向こうに二車線ある。 違和感を覚えない方がどうかしてる。 そして気付いた後の「やっばいぁ」「ふふふ」と緊張感のない会話。 ミスは一万歩譲って仕方がないとしても、この態度はあり得ない。 恥ずかしげもなく公開するのもさらに おかしい 。 免許返納 を検討されては？",
    "tweet_id": "2066845061569298551",
    "url": "https://x.com/akky03104/status/2066845061569298551",
    "original_category": "免許返納義務化に賛成（高齢運転手の事故防止を最優先）",
    "original_stance": "義務化賛成",
    "is_opinion": true,
    "stance_restriction": 1.0,
    "stance_priority": 2.0,
    "emotional_intensity": 2.0,
    "confidence": 0.85,
    "summary": "危険運転への強い怒りと免許返納促し"
  },
  {
    "text": "よくみたけどお前が おかしい わ。 反省できねえみたいだし 免許返納 しろ。",
    "tweet_id": "2066361367180058996",
    "url": "https://x.com/Tama_555_Tama/status/2066361367180058996",
    "original_category": "免許返納義務化に反対（地方の生活維持や移動手段確保を重視）",
    "original_stance": "義務化反対",
    "is_opinion": true,
    "stance_restriction": 1.0,
    "stance_priority": 1.0,
    "emotional_intensity": 1.5,
    "confidence": 0.7,
    "summary": "不安全運転を批判し返納を求める怒りの投稿"
  },
  {
    "text": "運転マナー分からないや夜中騒音撒き散らすクソバイク運転手全て運転したり路上出ちゃだろ 免許返納 しろ常識やマナーすら分からない頭 おかしい クソ化け物共がよ",
    "tweet_id": "2065856256058015819",
    "url": "https://x.com/catcat2921/status/2065856256058015819",
    "original_category": "免許返納義務化に賛成（高齢運転手の事故防止を最優先）",
    "original_stance": "義務化賛成",
    "is_opinion": true,
    "stance_restriction": 1.5,
    "stance_priority": 1.5,
    "emotional_intensity": 2.0,
    "confidence": 0.85,
    "summary": "マナ欠如のライダー全てに返納求める怒り投稿"
  },
  {
    "text": "車間距離 おかしい 人 免許返納 してほしいわ🤢",
    "tweet_id": "2065643464793178311",
    "url": "https://x.com/nicestarguy/status/2065643464793178311",
    "original_category": "免許返納義務化に賛成（高齢運転手の事故防止を最優先）",
    "original_stance": "義務化賛成",
    "is_opinion": true,
    "stance_restriction": 1.0,
    "stance_priority": 1.0,
    "emotional_intensity": 1.0,
    "confidence": 0.7,
    "summary": "危険運転に不快感、返納を求める投稿"
  },
  {
    "text": "こういう おかしい のが乗るから車はマニュアル重ステで良い。 年齢を重ねて操作できなくなったら 免許返納 のタイミングでいいじゃん。 https://t.co/ytSLLaaYvI",
    "tweet_id": "2065385305788776580",
    "url": "https://x.com/bluesteel1990/status/2065385305788776580",
    "original_category": "免許返納義務化に賛成（高齢運転手の事故防止を最優先）",
    "original_stance": "義務化賛成",
    "is_opinion": true,
    "stance_restriction": -1.0,
    "stance_priority": 1.0,
    "emotional_intensity": 1.0,
    "confidence": 0.8,
    "summary": "操作困難になったら自主返納すべきとの意見"
  },
  {
    "text": "美作市、どういう優先順位なんですかね… 高齢者・ 免許返納 者の移動支援は後回しで こちらが先行なら順番が おかしい ですね",
    "tweet_id": "2065351741252702703",
    "url": "https://x.com/Ryudou_XX/status/2065351741252702703",
    "original_category": "免許返納義務化に反対（地方の生活維持や移動手段確保を重視）",
    "original_stance": "義務化反対",
    "is_opinion": true,
    "stance_restriction": 0.0,
    "stance_priority": 0.5,
    "emotional_intensity": 1.0,
    "confidence": 0.7,
    "summary": "市の予算優先順位を批判。返納者支援の充実を主張"
  },
  {
    "text": "前の車が変な運転するなって思ってたら 後ろから見ても携帯いじってるの見えて 発進も遅いし停止線は越える、ふらつく運転 頭 おかしい とか思えない まじで 免許返納 したがいい",
    "tweet_id": "2065054341455896753",
    "url": "https://x.com/jammer1120/status/2065054341455896753",
    "original_category": "免許返納義務化に賛成（高齢運転手の事故防止を最優先）",
    "original_stance": "義務化賛成",
    "is_opinion": true,
    "stance_restriction": 1.5,
    "stance_priority": 1.5,
    "emotional_intensity": 1.5,
    "confidence": 0.8,
    "summary": "危険運転を見て返納を促す感情的投稿"
  },
  {
    "text": "ぶっちゃけ危ない 運転 する 高齢者 ほど高齢 運転 者標識つけないから普通に 義務化 していいと思うけどな",
    "tweet_id": "2066655278729494774",
    "url": "https://x.com/mn6u_/status/2066655278729494774",
    "original_category": "免許返納義務化に賛成（高齢運転手の事故防止を最優先）",
    "original_stance": "義務化賛成",
    "is_opinion": true,
    "stance_restriction": 2.0,
    "stance_priority": 2.0,
    "emotional_intensity": 1.0,
    "confidence": 0.75,
    "summary": "高齢者運転の義務化支持、安全最優先の意見"
  },
  {
    "text": "高齢者 の 運転 ちょっとヤバいな 高齢者 マークつけるの 義務化 して欲しい",
    "tweet_id": "2066347382422610169",
    "url": "https://x.com/kn25q4hLPlICL2A/status/2066347382422610169",
    "original_category": "免許返納義務化に賛成（高齢運転手の事故防止を最優先）",
    "original_stance": "義務化賛成",
    "is_opinion": true,
    "stance_restriction": 1.0,
    "stance_priority": 1.0,
    "emotional_intensity": 0.5,
    "confidence": 0.75,
    "summary": "高齢者のマーク義務化を求め安全を重視する意見"
  },
  {
    "text": "93歳男性が 運転 する車が自転車をはねる 63歳男性が死亡 茨城・阿見町 #自民党 #国土交通省 #都道府県公安委員会 https://t.co/aFuuMBMFHV いい加減「 高齢者 自動ブレーキ搭載車」 義務化 とか法案作らないの？ そこに補助金（税金）付けるなら 燃える棺桶号中国EV補助金より余程納得できる。",
    "tweet_id": "2060705677589537128",
    "url": "https://x.com/Harukaze_ouri/status/2060705677589537128",
    "original_category": "免許返納義務化に賛成（高齢運転手の事故防止を最優先）",
    "original_stance": "義務化賛成",
    "is_opinion": true,
    "stance_restriction": 1.5,
    "stance_priority": 1.5,
    "emotional_intensity": 1.5,
    "confidence": 0.85,
    "summary": "高齢者の自動ブレーキ義務化を求め安全優先の意見"
  },
  {
    "text": "また 高齢者 。 自分は大丈夫って 運転 してるんだろうけど、確実に反射神経衰えてるからね・・もう返納 義務化 しましょう。",
    "tweet_id": "2060346382016491761",
    "url": "https://x.com/bbkeimaster/status/2060346382016491761",
    "original_category": "免許返納義務化に賛成（高齢運転手の事故防止を最優先）",
    "original_stance": "義務化賛成",
    "is_opinion": true,
    "stance_restriction": 2.0,
    "stance_priority": 2.0,
    "emotional_intensity": 1.0,
    "confidence": 0.8,
    "summary": "高齢者返納の義務化を強く主張"
  },
  {
    "text": "リアルで 運転 していたら中央線はみ出しながらタクシーに接近して煽ってる車発見 はやく自動 運転 実装して そして 高齢者 は自動 運転義務化 な",
    "tweet_id": "2060273956251373590",
    "url": "https://x.com/LuckySevenXrd/status/2060273956251373590",
    "original_category": "免許返納義務化に賛成（高齢運転手の事故防止を最優先）",
    "original_stance": "義務化賛成",
    "is_opinion": true,
    "stance_restriction": 2.0,
    "stance_priority": 2.0,
    "emotional_intensity": 1.0,
    "confidence": 0.8,
    "summary": "煽り運転体験を契機に高齢者の自動運行義務化を強く支持"
  },
  {
    "text": "まずミッションを 義務化 してほしいな 高齢者 は 運転 できないだろう",
    "tweet_id": "2060246248700219875",
    "url": "https://x.com/uriwifjfio/status/2060246248700219875",
    "original_category": "免許返納義務化に賛成（高齢運転手の事故防止を最優先）",
    "original_stance": "義務化賛成",
    "is_opinion": true,
    "stance_restriction": 2.0,
    "stance_priority": 2.0,
    "emotional_intensity": 1.0,
    "confidence": 0.8,
    "summary": "高齢者運転の義務化を求め安全優先の意見"
  }
]